{
    "reinforces": [
        {
            "xp_trip_ingot": 479,
            "heat_capacity": 1370,
            "malleability_midpoint": 1000,
            "folding_range": { "min": 400, "max": 700 },
            "xp_gain": { "min": 68.5, "max": 73.0 },
            "malleability_slope": 0.01,
            "heat_loss": { "min": 20, "max": 20},
            "cooling_slope": 0.01
        },
        {
            "xp_trip_ingot": 239,
            "heat_capacity": 1370,
            "malleability_midpoint": 1000,
            "folding_range": { "min": 400, "max": 700 },
            "xp_gain": { "min": 34.25, "max": 36.5 },
            "malleability_slope": 0.01,
            "heat_loss": { "min": 20, "max": 20},
            "cooling_slope": 0.01
        },
        {
            "xp_trip_ingot": 119,
            "heat_capacity": 1370,
            "malleability_midpoint": 1000,
            "folding_range": { "min": 400, "max": 700 },
            "xp_gain": { "min": 17.125, "max": 18.25 },
            "malleability_slope": 0.01,
            "heat_loss": { "min": 20, "max": 20},
            "cooling_slope": 0.01
        },
        {
            "xp_trip_ingot": 59,
            "heat_capacity": 1370,
            "malleability_midpoint": 1000,
            "folding_range": { "min": 400, "max": 700 },
            "xp_gain": { "min": 8.5625, "max": 9.125 },
            "malleability_slope": 0.01,
            "heat_loss": { "min": 20, "max": 20},
            "cooling_slope": 0.01
        },
        {
            "xp_trip_ingot": 29,
            "heat_capacity": 1370,
            "malleability_midpoint": 1000,
            "folding_range": { "min": 400, "max": 700 },
            "xp_gain": { "min": 4.28125, "max": 4.5625 },
            "malleability_slope": 0.01,
            "heat_loss": { "min": 20, "max": 20},
            "cooling_slope": 0.01
        }
    ]
}